{
  "metadata": {
    "name": "Simple Scene",
    "default camera": "main",
    "skybox scene": {
      "file": "simplescene_skybox.json",
      "texture": [ 2048, 2048 ]
    }
  },
  "models": {
    "cube": {
      "type": "ply",
      "geometry": "models/cube.ply",
      "merge geometry": true,
      "merge distance": 0.01
    },
    "suzanne": {
      "type": "ply",
      "geometry": "models/suzanne.ply",
      "merge geometry": true,
      "merge distance": 0.01
    },
    "level_endsection": {
      "type": "ply",
      "geometry": "models/opened cube.ply",
      "merge geometry": true,
      "merge distance": 0.01
    },
    "level_joiningsection": {
      "type": "ply",
      "geometry": "models/joining section.ply",
      "merge geometry": true,
      "merge distance": 0.01
    }
  },
  "layout": {
    "simple cube": {
      "model": "cube",
      "position": [ 8, -20, -2 ],
      "rotation": [ 0, 0, 0 ],
      "scale": [ 1, 1, 1 ],
      "shader": {
        "render": {
          "vertex": "simple",
          "fragment": "simple"
        },
        "shadow": {
          "vertex": "simple shadow",
          "fragment": "simple shadow",
          "geometry": "simple shadow"
        },
        "textures": {
          "colour": [ 1, 1, 1 ],
          "specular": [ 1, 1, 1 ],
          "normal": "textures/cube_normals.png",
          "reflection intensity": [ 0.1, 0.1, 0.1 ]
        },
        "phong": {
          "diffuse": [ 0.2, 0.2, 0.2 ],
          "specular": [ 0.2, 0.2, 0.2 ],
          "specular highlight": 32
        },
        "reflections": {
          "reflection": "simple cube",
          "mode": "iterative sampling"
        }
      }
    },
    "blender suzanne": {
      "model": "suzanne",
      "position": [ 0, 2, 0 ],
      "rotation": [ 0, 0, 0 ],
      "scale": [ 1, 1, 1 ],
      "shader": {
        "render": {
          "vertex": "simple",
          "fragment": "simple"
        },
        "shadow": {
          "vertex": "simple shadow",
          "fragment": "simple shadow",
          "geometry": "simple shadow"
        },
        "textures": {
          "colour": {
            "path": "textures/unnamed.jpg",
            "magnify filter": "nearest",
            "shrink filter": "nearest"
          },
          "specular": "textures/SuzanneSpecularMap.png",
          "reflection intensity": [ 0.4, 0.4, 0.4 ]
        },
        "phong": {
          "diffuse": [ 0.4, 0.4, 0.4 ],
          "specular": [ 0.2, 0.2, 0.2 ],
          "specular highlight": 32
        },
        "reflections": {
          "reflection": "level section 2 reflection",
          "mode": "iterative sampling"
        }
      }
    },
    "level section 1": {
      "model": "level_endsection",
      "position": [ 10, 0, 0 ],
      "rotation": [ 90, 270, 0 ],
      "scale": [ 5, 5, 5 ],
      "invert normals": true,
      "shader": {
        "render": {
          "vertex": "simple",
          "fragment": "simple"
        },
        "shadow": {
          "vertex": "simple shadow",
          "fragment": "simple shadow",
          "geometry": "simple shadow"
        },
        "textures": {
          "colour": [ 1, 1, 1 ],
          "specular": [ 1.0, 1.0, 1.0 ],
          "reflection intensity": [ 0.1, 0.1, 0.1 ]
        },
        "phong": {
          "diffuse": [ 0.2, 0.2, 0.2 ],
          "specular": [ 0.2, 0.2, 0.2 ],
          "specular highlight": 32
        },
        "reflections": {
          "reflection": "level section 1 reflection",
          "mode": "oriented bounding box"
        }
      }
    },
    "level section 2": {
      "model": "level_joiningsection",
      "position": [ 0, 0, 0 ],
      "rotation": [ 0, 0, 0 ],
      "scale": [ 5, 5, 5 ],
      "invert normals": true,
      "shader": {
        "render": {
          "vertex": "simple",
          "fragment": "simple"
        },
        "shadow": {
          "vertex": "simple shadow",
          "fragment": "simple shadow",
          "geometry": "simple shadow"
        },
        "textures": {
          "colour": [ 1, 1, 1 ],
          "specular": [ 1.0, 1.0, 1.0 ],
          "reflection intensity": [ 0.1, 0.1, 0.1 ]
        },
        "phong": {
          "diffuse": [ 0.2, 0.2, 0.2 ],
          "specular": [ 0.2, 0.2, 0.2 ],
          "specular highlight": 32
        },
        "reflections": {
          "reflection": "level section 2 reflection",
          "mode": "oriented bounding box"
        }
      }
    },
    "level section 3": {
      "model": "level_endsection",
      "position": [ 10, -20, 0 ],
      "rotation": [ 90, 270, 0 ],
      "scale": [ 5, 5, 5 ],
      "invert normals": true,
      "shader": {
        "render": {
          "vertex": "simple",
          "fragment": "simple"
        },
        "shadow": {
          "vertex": "simple shadow",
          "fragment": "simple shadow",
          "geometry": "simple shadow"
        },
        "textures": {
          "colour": [ 1, 1, 1 ],
          "specular": [ 1.0, 1.0, 1.0 ],
          "reflection intensity": [ 0.1, 0.1, 0.1 ]
        },
        "phong": {
          "diffuse": [ 0.2, 0.2, 0.2 ],
          "specular": [ 0.2, 0.2, 0.2 ],
          "specular highlight": 32
        },
        "reflections": {
          "reflection": "level section 3 reflection",
          "mode": "oriented bounding box"
        }
      }
    }
  },
  "cameras": {
    "main": {
      "position": [ 0, 0, 0 ],
      "rotation": [ 90, 0, -90 ],
      "clips": [ 0.1, 100 ],
      "fov": 60
    }
  },
  "shaders": {
    "fragment": {
      "simple": "shaders/simple.frag",
      "simple shadow": "shaders/simple_shadow.frag"
    },
    "vertex": {
      "simple": "shaders/simple.vert",
      "simple shadow": "shaders/simple_shadow.vert"
    },
    "geometry": {
      "simple shadow": "shaders/simple_shadow.geom"
    }
  },
  "lighting": {
    "ambient": [ 0.3, 0.3, 0.3 ],
    "point lights": {
      "simple light": {
        "position": [ 0, -10, 0 ],
        "intensity": [ 1, 1, 1 ],
        "shadows": false,
        "shadow texture": [ 2048, 2048 ],
        "shadow clips": [ 0.1, 100 ],
        "dynamic draw": [ "simple cube", "blender suzanne" ],
        "static draw": [ "level section 1", "level section 2", "level section 3" ],
        "dynamic refresh rate": 10
      },
      "simple light 2": {
        "position": [ 14, -20, 0 ],
        "intensity": [ 1, 1, 1 ],
        "shadows": false,
        "shadow texture": [ 2048, 2048 ],
        "shadow clips": [ 0.1, 100 ],
        "dynamic draw": [ "simple cube", "blender suzanne" ],
        "static draw": [ "level section 1", "level section 2", "level section 3" ],
        "dynamic refresh rate": 10
      }
    }
  },
  "reflections": {
    "level section 2 reflection": {
      "position": [ 0, -7.5, 0 ],
      "dynamic draw": [ "blender suzanne", "simple cube" ],
      "static draw": [ "level section 1", "level section 2", "level section 3" ],
      "dynamic refresh rate": 10,
      "clips": [ 0.1, 100 ],
      "texture": [ 1024, 1024 ],
      "corrections": {
        "oriented bounding box": {
          "dimensions": [ 10, 35, 10 ],
          "position": [ 0, -7.5, 0 ],
          "rotation": [ 0, 0, 0 ]
        },
        "iterative sampling": {
          "iterations": 0
        }
      }
    },
    "simple cube": {
      "position": [ 8, -20, -2 ],
      "dynamic draw": [ "blender suzanne" ],
      "static draw": [ "level section 1", "level section 2", "level section 3" ],
      "dynamic refresh rate": 10,
      "clips": [ 0.1, 100 ],
      "texture": [ 1024, 1024 ],
      "corrections": {
        "oriented bounding box": {
          "dimensions": [ 1, 1, 1 ],
          "position": [ 0, 0, 0 ],
          "rotation": [ 0, 0, 0 ]
        },
        "iterative sampling": {
          "iterations": 0
        }
      }
    },
    "level section 1 reflection": {
      "position": [ 5, 0, 0 ],
      "dynamic draw": [ "blender suzanne", "level section 1", "level section 2", "level section 3" ],
      "static draw": [],
      "dynamic refresh rate": 10,
      "clips": [ 0.1, 100 ],
      "texture": [ 1024, 1024 ],
      "corrections": {
        "oriented bounding box": {
          "dimensions": [ 20, 10, 10 ],
          "position": [ 5, 0, 0 ],
          "rotation": [ 0, 0, 0 ]
        },
        "iterative sampling": {
          "iterations": 0
        }
      }
    },
    "level section 3 reflection": {
      "position": [ 5, -20, 0 ],
      "dynamic draw": [ "blender suzanne", "level section 1", "level section 2", "level section 3" ],
      "static draw": [],
      "dynamic refresh rate": 10,
      "clips": [ 0.1, 100 ],
      "texture": [ 1024, 1024 ],
      "corrections": {
        "oriented bounding box": {
          "dimensions": [ 20, 10, 10 ],
          "position": [ 5, -20, 0 ],
          "rotation": [ 0, 0, 0 ]
        },
        "iterative sampling": {
          "iterations": 0
        }
      }
    }
  }
}